ko2kana/__init__.py
ko2kana/english.py
ko2kana/g2pk3.py
ko2kana/idioms.txt
ko2kana/k2j.py
ko2kana/korean.py
ko2kana/numerals.py
ko2kana/regular.py
ko2kana/rules.txt
ko2kana/special.py
ko2kana/table.csv
ko2kana/utils.py
ko2kana-1.8.dist-info/LICENSE
ko2kana-1.8.dist-info/METADATA
ko2kana-1.8.dist-info/WHEEL
ko2kana-1.8.dist-info/top_level.txt
ko2kana-1.8.dist-info/RECORD
