Metadata-Version: 2.1
Name: ko2kana
Version: 1.8
Summary: Korean to Katakana
Home-page: https://github.com/kdrkdrkdr/ko2kana
Author: kdr
Author-email: kdrhacker1234@gmail.com
License: MIT
Classifier: Programming Language :: Python :: 3
Classifier: Programming Language :: Python :: 3.7
Classifier: Programming Language :: Python :: 3.8
Classifier: Programming Language :: Python :: 3.9
Classifier: Programming Language :: Python :: 3.10
Classifier: Programming Language :: Python :: 3.11
Classifier: Programming Language :: Python :: 3.12
Classifier: License :: OSI Approved :: MIT License
Classifier: Operating System :: OS Independent
License-File: LICENSE
Requires-Dist: jamo
Requires-Dist: g2p-en
